adaptive_hierarchical_text_clustering/__init__.py
adaptive_hierarchical_text_clustering/clustering.py
adaptive_hierarchical_text_clustering-0.1.0.dist-info/METADATA
adaptive_hierarchical_text_clustering-0.1.0.dist-info/WHEEL
adaptive_hierarchical_text_clustering-0.1.0.dist-info/top_level.txt
adaptive_hierarchical_text_clustering-0.1.0.dist-info/RECORD
