Metadata-Version: 2.1
Name: adaptive-hierarchical-text-clustering
Version: 0.1.0
Summary: A library for extracting hierarchical structure from unstructured text using adaptive clustering
Home-page: https://github.com/john-ades/adaptive-hierarchical-text-clustering
Author: John Ades
Author-email: John Ades <john.a.ades@gmail.com>
License: MIT
Project-URL: Homepage, https://github.com/john-ades/adaptive-hierarchical-text-clustering
Project-URL: Bug Tracker, https://github.com/john-ades/adaptive-hierarchical-text-clustering/issues
Classifier: Development Status :: 3 - Alpha
Classifier: Intended Audience :: Developers
Classifier: License :: OSI Approved :: MIT License
Classifier: Operating System :: OS Independent
Classifier: Programming Language :: Python :: 3
Classifier: Programming Language :: Python :: 3.7
Classifier: Programming Language :: Python :: 3.8
Classifier: Programming Language :: Python :: 3.9
Classifier: Programming Language :: Python :: 3.10
Classifier: Programming Language :: Python :: 3.11
Classifier: Programming Language :: Python :: 3.12
Requires-Python: >=3.7
Requires-Dist: numpy >=1.19.0
Provides-Extra: dev
Requires-Dist: pytest >=6.0 ; extra == 'dev'
Requires-Dist: anytree >=2.8.0 ; extra == 'dev'
Requires-Dist: sentence-transformers >=2.0.0 ; extra == 'dev'
